pyqt_ani_abstractbutton/__init__.py
pyqt_ani_abstractbutton/aniAbstractButton.py
pyqt_ani_abstractbutton-0.0.4.dist-info/LICENSE
pyqt_ani_abstractbutton-0.0.4.dist-info/METADATA
pyqt_ani_abstractbutton-0.0.4.dist-info/WHEEL
pyqt_ani_abstractbutton-0.0.4.dist-info/top_level.txt
pyqt_ani_abstractbutton-0.0.4.dist-info/RECORD
