Metadata-Version: 2.1
Name: pyqt-ani-abstractbutton
Version: 0.0.4
Summary: PyQt QAbstractButton for animation
Home-page: https://github.com/yjg30737/pyqt-ani-abstractbutton.git
Author: Jung Gyu Yoon
Author-email: yjg30737@gmail.com
License: MIT
Platform: UNKNOWN
License-File: LICENSE
Requires-Dist: PyQt5 (>=5.8)
